bio_tools/bio_tools.py
bio_tools-0.1.0.dist-info/LICENSE
bio_tools-0.1.0.dist-info/WHEEL
bio_tools-0.1.0.dist-info/METADATA
bio_tools-0.1.0.dist-info/RECORD
