Metadata-Version: 2.1
Name: bio-tools
Version: 0.1.0
Summary: Tools for computational biology
License: MIT
Author: Luke Schiefelbein
Author-email: luke.schiefelbein@gmail.com
Requires-Python: >=3.8,<4.0
Classifier: License :: OSI Approved :: MIT License
Classifier: Programming Language :: Python :: 3
Classifier: Programming Language :: Python :: 3.8
Classifier: Programming Language :: Python :: 3.9
Requires-Dist: pandas (>=1.2.4,<2.0.0)
